dserver_direct_mongo_plugin/__init__.py
dserver_direct_mongo_plugin/config.py
dserver_direct_mongo_plugin/schemas.py
dserver_direct_mongo_plugin/utils.py
dserver_direct_mongo_plugin/version.py
dserver_direct_mongo_plugin-0.4.2.dist-info/licenses/LICENSE
dserver_direct_mongo_plugin-0.4.2.dist-info/METADATA
dserver_direct_mongo_plugin-0.4.2.dist-info/WHEEL
dserver_direct_mongo_plugin-0.4.2.dist-info/entry_points.txt
dserver_direct_mongo_plugin-0.4.2.dist-info/top_level.txt
dserver_direct_mongo_plugin-0.4.2.dist-info/RECORD
