Metadata-Version: 2.4
Name: dserver-direct-mongo-plugin
Version: 0.4.2
Summary: This plugin allows to submit mongo queries and aggregation pipelines directly an underlying MongoDB.
Author-email: "Johannes L. Hörmann" <johannes.laurin@gmail.com>
License: MIT License
Project-URL: Documentation, https://dserver-direct-mongo-plugin.readthedocs.io
Project-URL: Repository, https://github.com/livMatS/dserver-direct-mongo-plugin
Project-URL: Changelog, https://github.com/livMatS/dserver-direct-mongo-plugin/blob/main/CHANGELOG.rst
License-File: LICENSE
Requires-Dist: dtoolcore>=3.18.0
Requires-Dist: dservercore>0.18.0
Provides-Extra: test
Requires-Dist: dservercore; extra == "test"
Requires-Dist: dserver-retrieve-plugin-mongo; extra == "test"
Requires-Dist: dserver-search-plugin-mongo; extra == "test"
Requires-Dist: pytest; extra == "test"
Requires-Dist: pytest-cov; extra == "test"
Dynamic: license-file
